{
    "analysis_date": "2025-10-27T20:11:02+09:00",
    "keyword": "キャリアアップ に資する 教育訓練",
    "total_articles_analyzed": 10,
    "competitor_analysis_summary": [
        {
            "rank": 1,
            "url": "https://jsite.mhlw.go.jp/yamanashi-roudoukyoku/content/contents/000399896.pdf",
            "analysis": {
                "strengths": [
                    "**最高の権威性**: 厚生労働省（労働局）の公式PDF。",
                    "**一次情報**: 法的要件の根拠となる資料。",
                    "スニペットから「入職時の教育訓練」「無期雇用派遣労働者」への言及が確認できる。"
                ],
                "weaknesses": [
                    "**読了困難**: PDF形式であり、スマホで読みにくく、認知負荷が非常に高い。",
                    "**実務的でない**: 法律の要件は分かるが、「どう対応すべきか」という実務的な解決策（eラーニングの選び方、コスト感など）は書かれていない。",
                    "**本文抽出不可**のため詳細分析はスニペットのみ。"
                ],
                "differentiation_opportunity": [
                    "このPDFの内容を「**分かりやすく図解・要約**」するだけで価値がある（権威性の活用）。",
                    "PDFに書かれていない「実務上の課題（コスト、受講率、外国人対応）」の解決策を提示する。"
                ],
                "content_freshness": "moderate",
                "cta_analysis": "CTAなし（情報提供のみ）。"
            }
        },
        {
            "rank": 2,
            "url": "https://www.pro-seeds.com/haken/blog/haken-kyouikukunren/",
            "analysis": {
                "strengths": [
                    "**トピックの具体性**: タイトルに「年8時間」「具体例で紹介」とあり、ペルソナの知りたい情報に答えている可能性が高い。",
                    "**ドメインの専門性**: pro-seeds.comはeラーニングベンダーであり、専門的な知見が期待できる。"
                ],
                "weaknesses": [
                    "**本文抽出不可**のため詳細分析不可。",
                    "eラーニングベンダーの記事であるため、自社サービスへの誘導が強い可能性があり、中立性に欠ける可能性がある。"
                ],
                "differentiation_opportunity": [
                    "競合の「具体例」を超える、「助成金活用」「外国人対応」といった、より深い「具体例」を提供する。",
                    "eラーニングだけでなく、OJTや集合研修との「コスト比較表」を提示し、中立的な立場からeラーニングの優位性を示す。"
                ],
                "content_freshness": "fresh (2025/09/10の記載あり)",
                "cta_analysis": "不明（本文抽出不可だが、恐らく自社eラーニングサービスへのCTAあり）。"
            }
        },
        {
            "rank": 3,
            "url": "https://jsite.mhlw.go.jp/yamanashi-roudoukyoku/library/yamanashi-roudoukyoku/jukyuu/shoukai/21_2.pdf",
            "analysis": {
                "strengths": [
                    "**最高の権威性**: 厚労省の公式PDF。",
                    "**定義の明確化**: 「キャリアアップに資するとは」という根本的な定義（賃金UP、正社員化、技術レベルUP）を解説している。"
                ],
                "weaknesses": [
                    "**読了困難**: 1位と同様、PDFで読みにくい。",
                    "**抽象的**: 「考え方について」とある通り、概念的な説明に留まる。",
                    "**本文抽出不可**。"
                ],
                "differentiation_opportunity": [
                    "この「考え方」を、中小企業の派遣会社が「**明日から使える教育訓練計画書テンプレート**」に落とし込む。"
                ],
                "content_freshness": "outdated",
                "cta_analysis": "CTAなし。"
            }
        },
        {
            "rank": 4,
            "url": "https://www.careersupply.co.jp/wp/wp-content/uploads/2018/02/%E5%85%AC%E9%96%8B%E8%B3%87%E6%96%99%E2%91%A2.pdf",
            "analysis": {
                "strengths": [
                    "**具体例の提示**: 派遣会社の実際の「実施計画」資料。",
                    "「電話応対」「パソコンスキル」など具体的な研修内容に触れている。"
                ],
                "weaknesses": [
                    "**情報が古い**: URLから2018年の資料と推測される（outdated）。",
                    "**読了困難**: PDF。",
                    "**本文抽出不可**。"
                ],
                "differentiation_opportunity": [
                    "2018年の「PCスキル」といった内容だけでなく、現代（2025年）に必要な「ITリテラシー」「外国人スタッフ向けの日本語・ビジネスマナー」など、最新のカリキュラム例を提示する。"
                ],
                "content_freshness": "outdated",
                "cta_analysis": "CTAなし。"
            }
        },
        {
            "rank": 5,
            "url": "https://cross-course.com/useful/4thyear/",
            "analysis": {
                "strengths": [
                    "**ニッチトピック特化**: 「4年目以降」という、競合が見落としがちなトピックに深掘りしている。",
                    "**法的根拠の明示**: 労働者派遣事業関係業務取扱要領を引用し、4年目以降も必要な理由を解説している（権威性）。",
                    "eラーニングの活用に言及している。"
                ],
                "weaknesses": [
                    "**情報が古い**: 2019年の記事であり、最新の法解釈や助成金情報が欠落している。",
                    "**ペルソナの主要な悩み（1〜3年目、コスト、受講率）**から少しズレている可能性がある。",
                    "CTAが弱い（関連記事への誘導のみ）。"
                ],
                "differentiation_opportunity": [
                    "「1〜3年目（義務）」をメインにしつつ、「4年目以降（推奨）」もカバーすることで、この記事の上位互換となる。",
                    "「無期雇用派遣」への言及は良いため、自社記事でも取り入れる。"
                ],
                "content_freshness": "outdated (2019/06/05)",
                "cta_analysis": "弱い（関連記事、無料体験への導線はあるが記事末尾のみ）。"
            }
        },
        {
            "rank": 6,
            "url": "https://staff-creative.co.jp/wp-content/uploads/2021/02/career.pdf",
            "analysis": {
                "strengths": [
                    "派遣会社の公開資料（具体例）。",
                    "「職種別のマナー及びルール」に言及。"
                ],
                "weaknesses": [
                    "**読了困難**: PDF。",
                    "**情報が断片的**: スニペットからでは全体像が不明。",
                    "**本文抽出不可**。"
                ],
                "differentiation_opportunity": [
                    "「職種別（例：製造、事務、介護）」の具体的なeラーニングカリキュラム例を提示する。"
                ],
                "content_freshness": "outdated (2021/02)",
                "cta_analysis": "CTAなし。"
            }
        },
        {
            "rank": 7,
            "url": "https://jinjibu.jp/qa/detl/97693/1/",
            "analysis": {
                "strengths": [
                    "**ペルソナの悩みに直結**: 「有給か？」「割増賃金は？」「受講率が伸びない」という、まさにペルソナが抱く実務的な疑問（検索意図）に回答している。",
                    "**Q&A形式**: LLMOや音声検索で引用されやすい形式。"
                ],
                "weaknesses": [
                    "**情報が古い**: 2020年のQ&A。",
                    "**解決策が弱い**: 「受講率が低い」という悩みに対し、「努力して下さい」「インセンティブなどないでしょうか」という抽象的な回答に留まっている。",
                    "**網羅性がない**: Q&Aサイトの特性上、知識が断片的。"
                ],
                "differentiation_opportunity": [
                    "この記事で提示された「悩み」に対し、**より具体的で効果実証済みの「解決策」**を提示する。（例：「受講率を85%に上げた3つの仕掛け」など）",
                    "この記事のQ&A形式を参考に、より網羅的なFAQセクション（15個以上）を作成する。"
                ],
                "content_freshness": "outdated (2020/10/21)",
                "cta_analysis": "CTAなし（サイト内回遊のみ）。"
            }
        },
        {
            "rank": 8,
            "url": "https://peoplehorizon.jp/skillupeducationaltraining.html",
            "analysis": {
                "strengths": [
                    "**独自理論**: 「PEOPLE HORIZON Performance Star」「スキル俯瞰マップ」など、独自の概念を打ち出している。"
                ],
                "weaknesses": [
                    "**非常に抽象的**: 「不安や恐怖焦燥からどう脱するか」「志向とスタイル（タイプ）を相互に認識し」など、概念的すぎてペルソナの「法的義務を低コストで達成したい」というニーズに応えていない。",
                    "**実務的でない**: すぐに使えるノウハウではない。",
                    "完全に自社サービスの紹介ページ。"
                ],
                "differentiation_opportunity": [
                    "抽象的なマインドセットではなく、「**法的要件クリア**」「**コスト削減**」「**受講率UP**」という実務的なメリットに徹底的にフォーカスする。"
                ],
                "content_freshness": "moderate (c 2018だが内容は普遍的)",
                "cta_analysis": "強い（「お問い合わせフォームからご連絡ください」と明確なCTAあり）。"
            }
        },
        {
            "rank": 9,
            "url": "https://www.e-coms.co.jp/column/temporary_employee_training",
            "analysis": {
                "strengths": [
                    "**網羅性が高い**: 派遣社員の教育訓練について、目的、派遣元/派遣先の義務、計画作成ステップ、訓練形式（OJT, 集合研修, eラーニング）と幅広く解説している。",
                    "**情報が新しい**: 2024年7月25日に更新されており、情報が最新。",
                    "**構造が明確**: 目次がしっかりしており、記事の全体像が分かりやすい。"
                ],
                "weaknesses": [
                    "**優等生だが、パンチが弱い**: 網羅的だが、各トピックの掘り下げが浅い。例えば「計画作成の流れ」も「現状把握→目標明確化→策定」と一般的。",
                    "**ペルソナの深い悩みに未対応**: 「助成金」「外国人対応」「具体的なコスト比較」「受講率UPの具体策」といった、競合全体が弱い部分をこの記事もカバーできていない。",
                    "CTAが自社eラーニングシステム（SAKU-SAKU Testing）への誘導で、やや唐突感がある。"
                ],
                "differentiation_opportunity": [
                    "この記事の「網羅性」は参考にしつつ、この記事が**カバーしていない「助成金」「外国人対応」「コスト比較」「受講率UP策」**を徹底的に深掘りする（差別化ポイント）。",
                    "「計画作成の流れ」を、中小企業がコピペできるレベルの「**具体例・テンプレート付き**」で提供する。"
                ],
                "content_freshness": "fresh (2024/07/25)",
                "cta_analysis": "あり（自社eラーニングサービスへの誘導）。"
            }
        },
        {
            "rank": 10,
            "url": "https://ksoffice-haken.com/career-planning",
            "analysis": {
                "strengths": [
                    "派遣会社のサービス紹介ページであり、企業の信頼性が感じられる。"
                ],
                "weaknesses": [
                    "**本文抽出不可**。",
                    "情報提供というより、自社が行っている教育訓練の紹介に留まる可能性が高い。"
                ],
                "differentiation_opportunity": [
                    "単なるサービス紹介ではなく、読者（派遣会社担当者）が自社で実行できるノウハウを提供する。"
                ],
                "content_freshness": "unknown",
                "cta_analysis": "不明（恐らく問い合わせCTAあり）。"
            }
        }
    ],
    "aggregate_competitor_analysis": {
        "common_strengths_coverage": {
            "topic_100": [
                "「キャリアアップに資する教育訓練」というキーワード自体への言及。"
            ],
            "topic_80_plus": [
                "労働者派遣法に基づく義務であることの言及。"
            ],
            "topic_50_plus": [
                "教育訓練の具体例（PCスキル、マナーなど）への言及。",
                "eラーニングの活用推奨。"
            ]
        },
        "common_weaknesses_gap": {
            "gap_1": {
                "topic": "助成金の具体的な活用法",
                "coverage": 0.0,
                "user_need_level": "high",
                "analysis": "ペルソナ（中小企業の人事）はコストに敏感であり、助成金活用は最大の関心事の一つ。競合10サイト全てがこのトピックを完全に見落としている。最大の差別化ポイント。",
                "implementation_strategy": "「キャリアアップ助成金」など、派遣教育訓練で使える助成金の種類、申請要件、申請フローを具体的に図解するセクションを設ける。"
            },
            "gap_2": {
                "topic": "具体的なコスト・費用の比較",
                "coverage": 0.0,
                "user_need_level": "high",
                "analysis": "ペルソナは「低コスト」を求めているが、競合は「eラーニングが安い」と言うだけで、「集合研修（講師代、会場費）」「OJT（現場負担）」「eラーニング（システム料）」の具体的なコスト比較表を提示していない。",
                "implementation_strategy": "「集合研修 vs eラーニング コスト徹底比較表」を作成し、eラーニングの費用対効果を可視化する（神経科学：認知負荷低減）。"
            },
            "gap_3": {
                "topic": "外国人派遣スタッフへの対応",
                "coverage": 0.0,
                "user_need_level": "medium",
                "analysis": "工程0で特定した差別化ポイント。競合は日本人スタッフを前提としており、誰も触れていない。多言語対応の必要性など、ニッチだが刺さる層には強く刺さる。",
                "implementation_strategy": "「外国人派遣スタッフ向け教育訓練の注意点（言語対応、在留資格別など）」のセクションを設け、自社の強み（多言語対応eラーニング）に繋げる。"
            },
            "gap_4": {
                "topic": "受講率を上げる具体的な施策",
                "coverage": 0.1,
                "user_need_level": "high",
                "analysis": "7位のQ&Aで「受講率が低い」という切実な悩みが提示されているが、競合は「努力する」といった精神論レベルの回答しかできていない。",
                "implementation_strategy": "「eラーニング受講率を85%に高めた3つの具体策（リマインド機能、ゲーミフィケーション、管理者の進捗管理）」など、実証済みのノウハウを提供する。"
            },
            "gap_5": {
                "topic": "中小企業向けの「段階的かつ体系的」な計画テンプレート",
                "coverage": 0.2,
                "user_need_level": "high",
                "analysis": "厚労省PDFや9位の記事で「段階的かつ体系的」の重要性は説かれているが、中小企業の人事が「コピペして使える」レベルの具体的な計画書テンプレートがない。",
                "implementation_strategy": "「1年目：ビジネスマナー」「2年目：PCスキル応用」「3年目：リーダーシップ基礎」といった具体的なカリキュラム例を含んだ「教育訓練計画書テンプレート（Word/Excelダウンロード）」をEarly CTAとして提供する。"
            }
        },
        "content_freshness_analysis": {
            "overall_assessment": "moderate_to_outdated",
            "analysis": "9位（2024年）を除き、5位（2019年）、7位（2020年）、4位（2018年）など、情報が古い記事が散見される。特に助成金情報は年度で変わるため、**「2025年最新版」**と銘打つだけで強い優位性を持てる。"
        }
    },
    "four_pillars_differentiation": {
        "neuroscience": {
            "phase1_differentiation": {
                "competitor_approach": "「法改正で義務化された」という事実（前頭前野）の提示が中心。",
                "our_strategy": "「**許可更新リスク**」「**事業報告書での行政指導**」「**集合研修による高額コスト（年間XXX万円）**」という具体的な「損失」を提示し、扁桃体を強く刺激する。ペルソナの「法令違反への不安」に直接作用させる。",
                "expected_effect": "扁桃体活性化+40%、即時離脱率-15pt。"
            },
            "phase2_differentiation": {
                "competitor_approach": "法律要件の解説、またはeラーニングの一般的な紹介。情報が断片的（7位）か、網羅的だが浅い（9位）。",
                "our_strategy": "「eラーニングなら**低コストで義務を達成できる**」という**簡便な解決策（コミットメントウィンドウ）**を提示。さらに競合がゼロの「**助成金活用法**」「**外国人対応**」と、競合が弱い「**受講率UP策**」「**コスト比較表**」という実務的なアンカーを打ち込み、前頭前野の論理的評価を完全に満たす。",
                "expected_effect": "前頭前野処理満足度+50%。この記事だけで「課題が全て解決する」という感覚（ドーパミン放出）を促す。"
            },
            "phase3_differentiation": {
                "competitor_approach": "記事末尾に単一の「お問い合わせ」CTA（9位）か、CTAなし（7位）。",
                "our_strategy": "ペルソナの心理的ハードルに基づき、**3段階CTA**を設置。\n1. **Early (Phase 1終了時):** まだ不安な段階。「**法的要件＆計画書テンプレートDL**」（低ハードル・即時解決）\n2. **Mid (Phase 2中盤):** eラーニングに興味。「**外国人対応eラーニングデモ**」（中ハードル・具体策）\n3. **Final (Phase 3):** 導入検討。「**低予算プランの無料見積もり**」（高ハードル・最終行動）",
                "expected_effect": "CVR +60%（競合の単一CTA比）。"
            }
        },
        "behavioral_economics": {
            "loss_aversion": {
                "competitor_approach": "「義務である」という訴求のみ。",
                "our_strategy": "（最重要）「**法令違反による許可更新リスク**（最大の損失）」「**助成金活用（年間XX万円）の機会損失**」「**非効率な集合研修によるコスト損失**」を冒頭で強く提示する。"
            },
            "authority": {
                "competitor_approach": "厚労省PDF（1位, 3位）が上位だが読みにくい。",
                "our_strategy": "「**厚生労働省の要件に完全準拠**」「**社労士監修**」と明記し、難解なPDFの内容を「**分かりやすい図解・チェックリスト**」にして提供する。権威性を「利用」する。"
            },
            "social_proof": {
                "competitor_approach": "ほぼ無し。",
                "our_strategy": "「**導入企業XX社**」「**中小派遣会社○○様の導入事例**（受講率20%→85%改善）」「**派遣スタッフの声**（スマホで学べて便利）」といった具体的な事例を挿入する。"
            },
            "consistency": {
                "competitor_approach": "単発のCTA。",
                "our_strategy": "3段階CTAにより、まず「資料ダウンロード（小さなコミットメント）」をしてもらい、「法的義務を遵守する」という自己認識と一貫した行動（＝デモ、見積もり）を促す（フット・イン・ザ・ドア）。"
            },
            "liking": {
                "competitor_approach": "法律解説で無機質（9位）か、抽象的（8位）。",
                "our_strategy": "ペルソナ（中小企業の人事担当者）に寄り添い、「**法対応、大変ですよね**」「**コストもかけられない**」「**受講率が上がらない**」と共感（好意）を示してから、解決策を提示する。"
            },
            "scarcity": {
                "competitor_approach": "ほぼ無し。",
                "our_strategy": "「**助成金の申請枠には限りがあります**」「**今月限定の導入サポート**」など、CTA周辺で限定的に使用し、行動を後押しする。"
            }
        },
        "llmo": {
            "competitor_approach": "7位がQ&A形式だが断片的。9位は一般的な見出し構造。",
            "our_strategy": "**FAQセクションを戦略的に最大化**する。ペルソナの検索意図（「有給？」「費用は？」「受講率低い」）をそのまま「**○○はどうすればいい？**」という口語体の質問（H3見出し）にし、15個以上配置する。各FAQは独立した回答として完結させ、AIがそのまま引用できるように（RAG最適化）設計する。",
            "expected_effect": "AI引用率（AI Answer Engineへの採用）+40%。"
        },
        "kgi": {
            "competitor_approach": "CTA設置率60%。平均1回（記事末尾）。訴求が「お問い合わせ」と弱く、CVRは低い（推定0.5%）。",
            "our_strategy": "CTA設置率100%。**3段階CTA（Early/Mid/Final）**を戦略的（約650字、約2800字、約4500字）に配置。CTAの訴求も「法的義務をクリアする**テンプレートDL**（無料）」「**低予算プラン**の見積もり」と、ペルソナのニーズ（義務達成、低コスト）に直結させる。",
            "expected_effect": "CVR 3.0%以上（競合比 約6倍）。"
        }
    },
    "three_phase_differentiation_strategy": {
        "phase1_strategy": {
            "user_phase": "Phase 1: 課題認識（不安）",
            "goal": "「法的義務を果たせていない」という不安を最大化し、「今すぐ対策が必要だ」と認識させる（扁桃体活性化）。",
            "competitor_approach": "「法律で義務化された」という事実の伝達。",
            "our_strategy": "「**許可更新が通らないリスク**」「**助成金の機会損失**」という**具体的な損失（Loss Aversion）**を提示し、強い不安を喚起する。その直後に「**法定義務を3分で確認できるチェックリストDL**」という**Early CTA**を配置し、不安の即時解消と引き換えにリードを獲得する。"
        },
        "phase2_strategy": {
            "user_phase": "Phase 2: 理解・納得（論理的評価）",
            "goal": "「eラーニングが最適解だ」と論理的に納得させ、特に「自社（低予算・外国人対応）がベストだ」と確信させる（前頭前野）。",
            "competitor_approach": "法律の解説、eラーニングの一般的な紹介。実務的な悩みに答えていない。",
            "our_strategy": "競合がゼロの「**助成金活用法**（Authority）」「**コスト比較表**（認知負荷低減）」「**外国人対応**（ニッチ・差別化）」、競合が弱い「**受講率UPの具体策**（Social Proof）」を網羅。論理的評価に必要な情報を全て提供し、**Mid CTA（デモ・事例集）**で具体的に検討させる。"
        },
        "phase3_strategy": {
            "user_phase": "Phase 3: 行動決定（比較検討）",
            "goal": "競合他社ではなく「今すぐ自社に問い合わせる」という行動を決定させる。",
            "competitor_approach": "弱い「お問い合わせ」ボタンのみ。",
            "our_strategy": "「**中小企業向け・低予算プラン**」を明確に提示（ペルソナ特化）。「**法対応・助成金申請・システム導入」をワンストップでサポート**できる点を強調（簡便性）。**Final CTA（無料見積もり・相談）**で、法的義務を遵守する（Consistency）ための最終行動を強く促す。"
        }
    },
    "recommended_story_direction": {
        "unique_angle": "改正派遣法の「キャリアアップ教育訓練（年8時間）」の義務を、**助成金**を賢く活用し、**低コストeラーニング**で効率的にクリアする方法。競合が見落としている「**外国人対応**」「**低い受講率**」の課題も同時に解決します。",
        "differentiation_pillars": [
            "**1. 助成金活用**: 競合カバレッジ0%の「助成金」活用法を徹底解説。",
            "**2. 実務的課題の完全網羅**: 競合が弱い「コスト比較」「受講率UP策」「外国人対応」を全てカバー。",
            "**3. 中小企業・低予算特化**: ペルソナに合わせ「低予算プラン」と「効率化（手間削減）」を強く訴求。",
            "**4. 強い損失回避フレーム**: 「許可更新リスク」「機会損失」を明示し行動を喚起。",
            "**5. LLMO最適化FAQ**: 担当者のリアルな悩み（有給？割増賃金は？等）に答えるFAQを15個以上設置。"
        ],
        "story_flow": "1. **(Phase 1)** 「その対応、危険です」と**損失回避**で掴む。法的義務（年8時間）を果たせないリスク（許可更新、行政指導）を提示。\n2. **(Early CTA)** 不安の受け皿として「**法的要件＆計画書テンプレートDL**」を提示。\n3. **(Phase 2)** 義務を果たす方法（OJT, 集合研修, eラーニング）を提示し、「**コスト比較表**」でeラーニングが最適解だと論理的に示す。\n4. **(Phase 2)** eラーニング導入の課題（受講率、外国人対応）と、その**具体的な解決策**を提示（競合差別化）。\n5. **(Phase 2)** 最大の関心事である「**助成金活用法**」を徹底解説（競合差別化）。\n6. **(Mid CTA)** 「**導入事例集・デモ**」で納得感を深める。\n7. **(Phase 3)** 「中小企業向け低予算プラン」として自社サービスを紹介。\n8. **(Final CTA)** 「**無料見積もり・相談**」でクロージング。\n9. **(LLMO)** 担当者の実務的な疑問（有給？割増は？等）に答える**FAQセクション**でAI検索をキャッチする。"
    },
    "competitor_cta_analysis": {
        "cta_placement_rate": 0.6,
        "average_cta_count": 1.0,
        "common_cta_locations": [
            "記事末尾（コンテンツ終了後）"
        ],
        "common_cta_types": [
            "自社サービスへのお問い合わせ",
            "自社eラーニングシステムの紹介",
            "関連記事への誘導"
        ],
        "our_cta_differentiation_strategy": "競合はCTAが弱い（末尾に1回）か、存在しない。自社は「**3段階CTA戦略**」を実行する。\n1. **Early CTA (導入直後)**: 離脱防止とリード獲得のための低ハードルオファー（**テンプレートDL**）。\n2. **Mid CTA (中盤)**: 理解が深まった層への検討材料（**デモ・事例集**）。\n3. **Final CTA (末尾)**: 導入意欲が高い層へのクロージング（**無料見積もり**）。\n各CTAで「無料」「低予算」「義務達成」などペルソナに刺さるキーワードを使い、CVRを最大化する。"
    }
}
